[{"name":"New Skill","id":"ast-mys","book":"assist","description":"","scope":"","animation":"","stats":"","effects":"","user":"rob","modified":"1430364878750","undefined":"","tools":"","hits":"2","anim_a":"","anim_b":""},{"name":"New Skill","id":"ast-boy","book":"assist","description":"","scope":"","animation":"","stats":"","effects":"","user":"rob","modified":"","undefined":"","tools":"","hits":"1","anim_a":"","anim_b":""},{"name":"New Skill","id":"ast-ing","book":"assist","description":"","scope":"","animation":"","stats":"","effects":"","user":"rob","hits":"1","anim_a":"","anim_b":""},{"name":"New Skill","id":"ast-phy","book":"assist","description":"","scope":"","animation":"","stats":"","effects":"","user":"rob","hits":"1","anim_a":"","anim_b":""},{"name":"New Skill","id":"ast-hib","book":"assist","description":"","scope":"","animation":"","stats":"","effects":"","user":"rob","hits":"1","anim_a":"","anim_b":""},{"id":"ast-row","name":"New Skill","book":"assist","description":"","scope":"","animation":"","stats":"","effects":"","user":"rob","hits":"1","anim_a":"","anim_b":""},{"name":"New Skill","id":"atk-axe","book":"attack","description":"","scope":"","animation":"","stats":"","effects":"","user":"rob","hits":"1","anim_a":"","anim_b":""},{"name":"New Skill","id":"atk-mace","book":"attack","description":"","scope":"","animation":"","stats":"","effects":"","user":"rob","hits":"1","anim_a":"","anim_b":""},{"name":"New Skill","id":"atk-wand","book":"attack","description":"","scope":"","animation":"","stats":"","effects":"","user":"rob","hits":"1","anim_a":"","anim_b":""},{"id":"atk-sword","name":"New Skill","book":"attack","description":"","scope":"","animation":"","stats":"","effects":"","user":"rob","hits":"1","anim_a":"","anim_b":""},{"name":"New Skill","id":"atk-dagger","book":"attack","description":"","scope":"","animation":"","stats":"","effects":"","user":"rob","hits":"1","anim_a":"","anim_b":""},{"id":"chant","name":"Chant","book":"","description":"","scope":"","animation":"","stats":"","effects":"","user":"hib","hits":"1","anim_a":"","anim_b":""},{"id":"dream","name":"Dream Spells","book":"","description":"","scope":"","animation":"","stats":"","effects":"","user":"hib","hits":"1","anim_a":"","anim_b":""},{"id":"nightmare","name":"Nightmare","book":"","description":"","scope":"","animation":"","stats":"","effects":"","user":"hib","hits":"1","anim_a":"","anim_b":""},{"id":"strike","name":"Sword Strike","book":"","description":"","scope":"","animation":"","stats":"","effects":"","user":"phy","modified":"","undefined":"","tools":"","hits":"1","anim_a":"","anim_b":""},{"id":"enrage","name":"Enrage2","book":"sword","description":"","scope":"","animation":"","stats":"","effects":"","user":"phy","modified":1428572982393,"undefined":"","tools":"","hits":"1","anim_a":"","anim_b":""},{"id":"hprage","name":"HP to RAGE","book":"sword","description":"","scope":"","animation":"","stats":"","effects":"","user":"phy","modified":"","undefined":"","tools":"","hits":"1","anim_a":"","anim_b":""},{"id":"powersmash","name":"Power Smash","book":"sword","description":"","scope":"","animation":"","stats":"","effects":"","user":"phy","modified":"","undefined":"","tools":"","hits":"1","anim_a":"","anim_b":""},{"id":"firebreath","name":"Fire Breath","book":"sword","description":"","scope":"","animation":"","stats":"","effects":"","user":"phy","modified":1428572744837,"undefined":"","tools":"","hits":"1","anim_a":"","anim_b":""},{"id":"staff","name":"Darkness","type":"staff","description":"","scope":"one","animation":"","stats":"","action":"","icon":"","effects":"","user":"boy","book":"","modified":"","undefined":"","tools":"","hits":"1","anim_a":"","anim_b":""},{"id":"warlock","name":"Warlock Spells","action":"","description":"","scope":"party","animation":"","stats":"","effects":"","user":"boy","book":"","modified":"1428883759544","undefined":"","tools":"","hits":"1","anim_a":"","anim_b":""},{"id":"flames","name":"Flames","type":"warlock","description":"","scope":"all","animation":"","stats":"","action":"warlock","icon":"","effects":"","user":"boy","book":"warlock","modified":"","undefined":"","tools":"","hits":"1","anim_a":"","anim_b":""},{"id":"fireburn","name":"Fire Burn","type":"warlock","description":"","scope":"one","animation":"","stats":"","action":"warlock","icon":"","effects":"","user":"boy","book":"warlock","modified":"","undefined":"","tools":"","hits":"1","anim_a":"","anim_b":""},{"id":"claw","name":"New Skill","action":"","description":"","scope":"","animation":"","stats":"","effects":"","user":"fox","book":"","hits":"1","anim_a":"","anim_b":""},{"id":"swipe","name":"New Skill","action":"","description":"","scope":"","animation":"","stats":"","effects":"","user":"fox","book":"","hits":"1","anim_a":"","anim_b":""},{"id":"form-human","name":"New Skill","action":"","description":"","scope":"","animation":"","stats":"","effects":"","user":"fox","book":"","hits":"1","anim_a":"","anim_b":""},{"id":"wand","name":"Wand","book":"","description":"","scope":"","animation":"","stats":"","effects":"","user":"ing","hits":"1","anim_a":"","anim_b":""},{"id":"witch","name":"Witch Spells","book":"","description":"","scope":"","animation":"","stats":"","effects":"","user":"ing","hits":"1","anim_a":"","anim_b":""},{"id":"xform-frog","name":"Tranform: Frog","book":"xform","description":"","scope":"","animation":"","stats":"","effects":"","user":"ing","modified":"1429860302553","hits":"1","anim_a":"","anim_b":""},{"id":"xform-chicken","name":"Transform: Chicken","book":"xform","description":"","scope":"","animation":"","stats":"","effects":"","user":"ing","modified":"1429860305473","hits":"1","anim_a":"","anim_b":""},{"id":"xform-bunny","name":"Transform: Bunny","book":"xform","description":"","scope":"","animation":"","stats":"","effects":"","user":"ing","modified":"1429860307835","hits":"1","anim_a":"","anim_b":""},{"id":"toxic","name":"Toxic","book":"","description":"","scope":"","animation":"","stats":"","effects":"","user":"ing","hits":"1","anim_a":"","anim_b":""},{"id":"missile","name":"Magic MIssile","book":"","description":"","scope":"","animation":"","stats":"","effects":"","user":"ing","hits":"1","anim_a":"","anim_b":""},{"id":"envelop","name":"Envelop","action":"","description":"","scope":"","animation":"","stats":"","effects":"","user":"mys","book":"","hits":"1","anim_a":"","anim_b":""},{"id":"soothe","name":"New Skill","action":"","description":"","scope":"","animation":"","stats":"","effects":"","user":"mys","book":"","hits":"1","anim_a":"","anim_b":""},{"id":"form-fox","name":"New Skill","action":"","description":"","scope":"","animation":"","stats":"","effects":"","user":"mys","book":"","hits":"1","anim_a":"","anim_b":""},{"id":"item","name":"Use Item","book":"","description":"","scope":"","animation":"","stats":"","effects":"","user":"","modified":"1429860182295","hits":"1","anim_a":"","anim_b":""},{"id":"xform","name":"Tranform","book":"xform","description":"","scope":"","animation":"","stats":"","effects":"","user":"ing","modified":"1429860318803","hits":"1","anim_a":"","anim_b":""},{"id":"sword","name":"Sword Skills","book":"","description":"","scope":"","animation":"","stats":"","effects":"","user":"phy","modified":"1429860654484","undefined":"","tools":"","hits":"1","anim_a":"","anim_b":""},{"name":"REPLACE WITH WEP TYPE","id":"robber","book":"","description":"","scope":"","animation":"","stats":"","effects":"","user":"rob","modified":"1430104796791","hits":"1","anim_a":"","anim_b":""},{"name":"Assistance","id":"assist","book":"","description":"","scope":"","animation":"","stats":"","effects":"","user":"rob","modified":"1429860804548","undefined":"","tools":"","hits":"1","anim_a":"","anim_b":""},{"id":"attack","name":"Enemy Attack TEMP","book":"","description":"","scope":"","animation":"","stats":"","effects":"","user":"enemy","modified":"1430104801322","hits":"1","anim_a":"","anim_b":""}]